sd_meh/__init__.py
sd_meh/merge.py
sd_meh/merge_methods.py
sd_meh/model.py
sd_meh/presets.py
sd_meh/rebasin.py
sd_meh/utils.py
sd_meh-0.9.5.dist-info/LICENSE.txt
sd_meh-0.9.5.dist-info/METADATA
sd_meh-0.9.5.dist-info/WHEEL
sd_meh-0.9.5.dist-info/RECORD
