Metadata-Version: 2.1
Name: sd-meh
Version: 0.9.5
Summary: stable diffusion merging execution helper
Home-page: https://github.com/s1dlx/meh
License: MIT
Author: s1dlx
Author-email: s1dlx@proton.me
Requires-Python: >=3.10,<4.0
Classifier: License :: OSI Approved :: MIT License
Classifier: Programming Language :: Python :: 3
Classifier: Programming Language :: Python :: 3.10
Classifier: Programming Language :: Python :: 3.11
Project-URL: Repository, https://github.com/s1dlx/meh
